django_apiview/__init__.py
django_apiview/apps.py
django_apiview/base.py
django_apiview/clients.py
django_apiview/exceptions.py
django_apiview/pack.py
django_apiview/urls.py
django_apiview/utils.py
django_apiview/version.py
django_apiview/views.py
django_apiview/extras/__init__.py
django_apiview/extras/cache_admin.py
django_apiview/helpers/__init__.py
django_apiview/helpers/auth.py
django_apiview/helpers/cache.py
django_apiview/helpers/cache_cleaners.py
django_apiview/helpers/cipher.py
django_apiview/helpers/request_methods.py
django_apiview/helpers/transformer.py
django_apiview/helpers/validators.py
django_apiview/management/__init__.py
django_apiview/management/commands/__init__.py
django_apiview/management/commands/list_cache_entries.py
django_apiview/migrations/__init__.py
django_apiview/plugins/__init__.py
django_apiview/plugins/request_methods.py
django_apiview/swagger_ui/__init__.py
django_apiview/swagger_ui/fields.py
django_apiview/swagger_ui/views.py
django_apiview/templates/swagger-ui/swagger_ui.html
django_apiview/templates/swagger-ui/swagger_ui_initializer.js.tmpl
django_apiview-1.0.32.dist-info/LICENSE
django_apiview-1.0.32.dist-info/METADATA
django_apiview-1.0.32.dist-info/WHEEL
django_apiview-1.0.32.dist-info/top_level.txt
django_apiview-1.0.32.dist-info/RECORD
