Metadata-Version: 2.1
Name: django-apiview
Version: 1.0.32
Summary: A set of django tools to help you create JSON service..
Author: Zhao JunXin
Author-email: zhaojunxin@zencore.cn
Maintainer: Zhao JunXin
Maintainer-email: zhaojunxin@zencore.cn
License: MIT
Keywords: django-apiview
Classifier: Development Status :: 5 - Production/Stable
Classifier: Intended Audience :: Developers
Classifier: Topic :: Software Development :: Libraries :: Python Modules
Classifier: License :: OSI Approved :: MIT License
Classifier: Programming Language :: Python :: 3
Classifier: Programming Language :: Python :: 3 :: Only
License-File: LICENSE
Requires-Dist: django
Requires-Dist: django-click
Requires-Dist: django-middleware-global-request >=0.3.1
Requires-Dist: django-middleware-request-id >=0.1.0
Requires-Dist: django-static-swagger-ui >=4.14.0.2
Requires-Dist: fastutils
Requires-Dist: zenutils >=0.3.6
Requires-Dist: bizerror >=0.4.9
Requires-Dist: magic-import
